P_EO/__init__.py
P_EO/common/__init__.py
P_EO/common/common.py
P_EO/common/config.py
P_EO/common/error.py
P_EO/common/log.py
P_EO/common/time_.py
P_EO/core/__init__.py
P_EO/core/action.py
P_EO/core/driver.py
P_EO/core/elements.py
P_EO/core/javascript.py
P_EO/core/page.py
P_EO/public_variables/__init__.py
P_EO/public_variables/public_variables.py
p_eo-1.5.3.dist-info/licenses/LICENSE
p_eo-1.5.3.dist-info/METADATA
p_eo-1.5.3.dist-info/WHEEL
p_eo-1.5.3.dist-info/top_level.txt
p_eo-1.5.3.dist-info/RECORD
