Metadata-Version: 2.4
Name: p_eo
Version: 1.5.3
Summary: Python Selenium 的二次封装
Home-page: https://gitee.com/Joker_JH/p_eo
Author: 御风
Author-email: eternallyyf@163.com
License: Apache License 2.0
Requires-Python: >=3.7
License-File: LICENSE
Requires-Dist: selenium>=4
Requires-Dist: webdrivermanager_cn>=2.1.0
Requires-Dist: python-dotenv
Requires-Dist: func_timeout==4.3.5
Dynamic: author
Dynamic: author-email
Dynamic: description
Dynamic: description-content-type
Dynamic: home-page
Dynamic: license
Dynamic: license-file
Dynamic: requires-dist
Dynamic: requires-python
Dynamic: summary
